vChatGPT/__init__.py
vChatGPT/__main__.py
vChatGPT/data/buzzer.wav
vChatGPT/scripts/__init__.py
vChatGPT/scripts/audio.py
vChatGPT/scripts/main.py
vChatGPT/scripts/ml.py
vChatGPT/scripts/utils.py
vChatGPT-1.1.dist-info/LICENSE
vChatGPT-1.1.dist-info/METADATA
vChatGPT-1.1.dist-info/WHEEL
vChatGPT-1.1.dist-info/top_level.txt
vChatGPT-1.1.dist-info/RECORD
