Metadata-Version: 2.1
Name: vChatGPT
Version: 1.1
Summary: Verbal ChatGPT
Home-page: https://github.com/ywatanabe1989/vChatGPT
Author: ywatanabe1989
Author-email: ywata1989@gmail.com
License: GPL3.0
Keywords: verbal ChatGPT,AI language model,learning English
Classifier: Programming Language :: Python :: 3
Classifier: License :: OSI Approved :: MIT License
Requires-Python: >=3.0
License-File: LICENSE
Requires-Dist: audio2numpy
Requires-Dist: soundcard
Requires-Dist: scipy
Requires-Dist: readchar
Requires-Dist: openai
Requires-Dist: Whisper
Requires-Dist: SpeechRecognition
Requires-Dist: gtts
